setup.cfg
setup.py
anonymoususage/__init__.py
anonymoususage/anonymoususage.py
anonymoususage/api.py
anonymoususage/exceptions.py
anonymoususage/tools.py
anonymoususage.egg-info/PKG-INFO
anonymoususage.egg-info/SOURCES.txt
anonymoususage.egg-info/dependency_links.txt
anonymoususage.egg-info/pbr.json
anonymoususage.egg-info/top_level.txt
anonymoususage/analysis/__init__.py
anonymoususage/analysis/database.py
anonymoususage/analysis/datamanager.py
anonymoususage/analysis/plots.py
anonymoususage/tables/__init__.py
anonymoususage/tables/sequence.py
anonymoususage/tables/state.py
anonymoususage/tables/statistic.py
anonymoususage/tables/table.py
anonymoususage/tables/timer.py