Metadata-Version: 1.1
Name: anonymoususage
Version: 1.14
Summary: Anonymously track user usage patterns and statistics.
Home-page: https://github.com/lobocv/anonymoususage
Author: Calvin Lobo
Author-email: calvinvlobo@gmail.com
License: UNKNOWN
Download-URL: https://github.com/lobocv/anonymoususage/tarball/1.14
Keywords: logging,usage,tracking,statistics,anonymous
Platform: UNKNOWN
